numparser
