Metadata-Version: 1.1
Name: numparser
Version: 0.0.2
Summary: Python library for parsing numbers from strings.
Home-page: https://github.com/sadovnychyi/numparser
Author: Dmitry Sadovnychyi
Author-email: numparser@dmit.ro
License: GNU General Public License v2.0
Keywords: numbers,parser,num,digits,digit
Platform: UNKNOWN
Classifier: Intended Audience :: Developers
Classifier: Operating System :: OS Independent
Classifier: License :: OSI Approved :: GNU Library or Lesser General Public License (LGPL)
Classifier: Programming Language :: Python
Classifier: Programming Language :: Python :: 2.6
Classifier: Programming Language :: Python :: 2.7
Classifier: Programming Language :: Python :: 3
Classifier: Programming Language :: Python :: 3.2
Classifier: Programming Language :: Python :: 3.3
Classifier: Programming Language :: Python :: 3.4
Classifier: Development Status :: 5 - Production/Stable
Classifier: Natural Language :: English
Classifier: Topic :: Software Development :: Libraries :: Python Modules
Classifier: Topic :: Text Processing :: Linguistic
